{
  "properties": {
    "config": {
      "properties": {
        "client_errors_severity": {
          "default": "info",
          "enum": [
            "alert",
            "crit",
            "debug",
            "emerg",
            "err",
            "info",
            "notice",
            "warning"
          ],
          "type": "string"
        },
        "custom_fields_by_lua": {
          "additionalProperties": {
            "type": "string"
          },
          "description": "Lua code as a key-value map",
          "type": "object"
        },
        "host": {
          "default": "logs-01.loggly.com",
          "description": "A string representing a host name, such as example.com.",
          "type": "string"
        },
        "key": {
          "type": "string",
          "x-encrypted": true,
          "x-referenceable": true,
          "description": "\nThis field is [referenceable](/gateway/entities/vault/#how-do-i-reference-secrets-stored-in-a-vault). \nThis field is [encrypted](/gateway/keyring/)."
        },
        "log_level": {
          "default": "info",
          "enum": [
            "alert",
            "crit",
            "debug",
            "emerg",
            "err",
            "info",
            "notice",
            "warning"
          ],
          "type": "string"
        },
        "port": {
          "default": 514,
          "description": "An integer representing a port number between 0 and 65535, inclusive.",
          "maximum": 65535,
          "minimum": 0,
          "type": "integer"
        },
        "server_errors_severity": {
          "default": "info",
          "enum": [
            "alert",
            "crit",
            "debug",
            "emerg",
            "err",
            "info",
            "notice",
            "warning"
          ],
          "type": "string"
        },
        "successful_severity": {
          "default": "info",
          "enum": [
            "alert",
            "crit",
            "debug",
            "emerg",
            "err",
            "info",
            "notice",
            "warning"
          ],
          "type": "string"
        },
        "tags": {
          "default": [
            "kong"
          ],
          "items": {
            "type": "string"
          },
          "type": "array"
        },
        "timeout": {
          "default": 10000,
          "type": "number"
        }
      },
      "required": [
        "key"
      ],
      "type": "object"
    },
    "consumer": {
      "additionalProperties": false,
      "description": "If set, the plugin will activate only for requests where the specified has been authenticated. (Note that some plugins can not be restricted to consumers this way.). Leave unset for the plugin to activate regardless of the authenticated Consumer.",
      "properties": {
        "id": {
          "type": "string"
        }
      },
      "type": "object"
    },
    "protocols": {
      "default": [
        "grpc",
        "grpcs",
        "http",
        "https"
      ],
      "description": "A set of strings representing protocols.",
      "items": {
        "description": "A string representing a protocol, such as HTTP or HTTPS.",
        "enum": [
          "grpc",
          "grpcs",
          "http",
          "https",
          "tcp",
          "tls",
          "tls_passthrough",
          "udp",
          "ws",
          "wss"
        ],
        "type": "string"
      },
      "type": "array"
    },
    "route": {
      "additionalProperties": false,
      "description": "If set, the plugin will only activate when receiving requests via the specified route. Leave unset for the plugin to activate regardless of the route being used.",
      "properties": {
        "id": {
          "type": "string"
        }
      },
      "type": "object"
    },
    "service": {
      "additionalProperties": false,
      "description": "If set, the plugin will only activate when receiving requests via one of the routes belonging to the specified Service. Leave unset for the plugin to activate regardless of the Service being matched.",
      "properties": {
        "id": {
          "type": "string"
        }
      },
      "type": "object"
    }
  },
  "required": [
    "config"
  ]
}